pptx_tools/__init__.py
pptx_tools/audio_utils.py
pptx_tools/slide_info.py
pptx_tools/slide_transition.py
pptx_tools/subprocess_utils.py
pptx_tools/utils.py
pptx_tools/video_utils.py
pptx_tools/apps/__init__.py
pptx_tools/apps/slide_add_voice.py
pptx_tools/apps/slide_check_fonts.py
pptx_tools/apps/slide_delete_notes.py
pptx_tools/apps/slide_manual_transition.py
pptx_tools/apps/slide_video_formatter.py
pptx_tools/data/__init__.py
pptx_tools/data/hello.pptx
pptx_tools/data/transparent.png
pptx_tools/tts/__init__.py
pptx_tools/tts/azure_tts.py
pptx_tools/tts/azure_tts_voice.py
pptx_tools/tts/google_tts.py
pptx_tools/tts/google_tts_voice.py
tests/__init__.py
tests/pptx_tools/__init__.py
tests/pptx_tools/test_slide_add_voice.py
pptx_tools-0.1.10.dist-info/LICENSE
pptx_tools-0.1.10.dist-info/METADATA
pptx_tools-0.1.10.dist-info/WHEEL
pptx_tools-0.1.10.dist-info/entry_points.txt
pptx_tools-0.1.10.dist-info/top_level.txt
pptx_tools-0.1.10.dist-info/RECORD
