Metadata-Version: 2.1
Name: pptx-tools
Version: 0.1.10
Summary: A power point tools
Home-page: https://github.com/iory/pptx-tools
Author: iory
Author-email: ab.ioryz@gmail.com
License: MIT
Classifier: Development Status :: 5 - Production/Stable
Classifier: Intended Audience :: Developers
Classifier: Natural Language :: English
Classifier: License :: OSI Approved :: MIT License
Classifier: Programming Language :: Python
Classifier: Programming Language :: Python :: 3.5
Classifier: Programming Language :: Python :: 3.6
Classifier: Programming Language :: Python :: 3.7
Classifier: Programming Language :: Python :: Implementation :: CPython
License-File: LICENSE
Requires-Dist: coloredlogs
Requires-Dist: extendedos >=0.1.5
Requires-Dist: google-cloud-speech
Requires-Dist: google-cloud-texttospeech
Requires-Dist: langdetect
Requires-Dist: lxml
Requires-Dist: pydub
Requires-Dist: python-pptx
Requires-Dist: scikit-video
Requires-Dist: termcolor
Requires-Dist: tqdm
Requires-Dist: pathlib ; python_version < "3.0"
Provides-Extra: all
Requires-Dist: coloredlogs ; extra == 'all'
Requires-Dist: extendedos >=0.1.5 ; extra == 'all'
Requires-Dist: google-cloud-speech ; extra == 'all'
Requires-Dist: google-cloud-texttospeech ; extra == 'all'
Requires-Dist: langdetect ; extra == 'all'
Requires-Dist: lxml ; extra == 'all'
Requires-Dist: pydub ; extra == 'all'
Requires-Dist: python-pptx ; extra == 'all'
Requires-Dist: scikit-video ; extra == 'all'
Requires-Dist: termcolor ; extra == 'all'
Requires-Dist: tqdm ; extra == 'all'
Requires-Dist: azure-cognitiveservices-speech ; extra == 'all'
Requires-Dist: pathlib ; (python_version < "3.0") and extra == 'all'
Provides-Extra: azure
Requires-Dist: azure-cognitiveservices-speech ; extra == 'azure'
